py_framels-0.7.7.dist-info/METADATA
py_framels-0.7.7.dist-info/WHEEL
py_framels/__init__.py
py_framels/py_framels.cpython-311-aarch64-linux-gnu.so
py_framels-0.7.7.dist-info/RECORD
