Metadata-Version: 2.4
Name: py-framels
Version: 0.7.7
Classifier: Programming Language :: Rust
Classifier: Programming Language :: Python :: Implementation :: CPython
Classifier: Programming Language :: Python :: Implementation :: PyPy
Summary: Python bindings for the framels library
Requires-Python: >=3.7
